autoapi_validator/__init__.py
autoapi_validator/__main__.py
autoapi_validator/errors.py
autoapi_validator/loader.py
autoapi_validator/validator.py
autoapi_validator/integrations/__init__.py
autoapi_validator/integrations/django.py
autoapi_validator/integrations/fastapi.py
autoapi_validator/integrations/flask.py
autoapi_validator-0.1.0.dist-info/licenses/LICENSE
autoapi_validator-0.1.0.dist-info/METADATA
autoapi_validator-0.1.0.dist-info/WHEEL
autoapi_validator-0.1.0.dist-info/entry_points.txt
autoapi_validator-0.1.0.dist-info/top_level.txt
autoapi_validator-0.1.0.dist-info/RECORD
