Metadata-Version: 2.4
Name: autoapi-validator
Version: 0.1.0
Summary: Automatic OpenAPI request & response validator
Author: Santhosh
License: MIT
Project-URL: Homepage, https://github.com/santhosh/autoapi-validator
Project-URL: Repository, https://github.com/santhosh/autoapi-validator
Project-URL: Issues, https://github.com/santhosh/autoapi-validator/issues
Keywords: openapi,swagger,api,validator,testing
Classifier: Development Status :: 3 - Alpha
Classifier: Intended Audience :: Developers
Classifier: Topic :: Software Development :: Testing
Classifier: Topic :: Software Development :: Quality Assurance
Classifier: License :: OSI Approved :: MIT License
Classifier: Programming Language :: Python :: 3
Classifier: Programming Language :: Python :: 3.8
Classifier: Programming Language :: Python :: 3.9
Classifier: Programming Language :: Python :: 3.10
Classifier: Programming Language :: Python :: 3.11
Classifier: Programming Language :: Python :: 3.12
Requires-Python: >=3.8
License-File: LICENSE
Requires-Dist: pyyaml>=6.0
Requires-Dist: jsonschema>=4.0.0
Requires-Dist: requests>=2.28.0
Provides-Extra: fastapi
Requires-Dist: fastapi>=0.100.0; extra == "fastapi"
Requires-Dist: uvicorn>=0.23.0; extra == "fastapi"
Provides-Extra: flask
Requires-Dist: flask>=2.0.0; extra == "flask"
Provides-Extra: django
Requires-Dist: django>=3.2; extra == "django"
Provides-Extra: dev
Requires-Dist: pytest>=7.0.0; extra == "dev"
Requires-Dist: pytest-cov>=4.0.0; extra == "dev"
Requires-Dist: black>=23.0.0; extra == "dev"
Requires-Dist: flake8>=6.0.0; extra == "dev"
Requires-Dist: fastapi>=0.100.0; extra == "dev"
Requires-Dist: uvicorn>=0.23.0; extra == "dev"
Requires-Dist: httpx>=0.24.0; extra == "dev"
Requires-Dist: flask>=2.0.0; extra == "dev"
Dynamic: license-file
